LICENSE
README.md
setup.cfg
setup.py
retico_core/core/abstract.py
retico_core/core/audio.py
retico_core/core/debug.py
retico_core/core/dialogue.py
retico_core/core/network.py
retico_core/core/text.py
retico_core/core/version.py
retico_core/core/visual.py
retico_core_core.egg-info/PKG-INFO
retico_core_core.egg-info/SOURCES.txt
retico_core_core.egg-info/dependency_links.txt
retico_core_core.egg-info/requires.txt
retico_core_core.egg-info/top_level.txt