Metadata-Version: 2.1
Name: retico-core-core
Version: 0.1.7
Summary: A framework for real time incremental dialogue processing.
Author: Ryan Pacheco
Author-email: ryanpacheco413@u.boisestate.edu
Keywords: retico,framework,incremental,dialogue,dialog
Classifier: Development Status :: 2 - Pre-Alpha
Classifier: Programming Language :: Python :: 3
Classifier: License :: OSI Approved :: Apache Software License
Requires-Python: >=3.6, <4
License-File: LICENSE
Requires-Dist: pyaudio>=0.2.12
Requires-Dist: nltk>=3.8.1
